[

  {
  "restaurants":
    {
    "title": "מסעדות ובתי קפה",
    "text_path": "content/activities/restaurants_he.txt",
    "links": 
     [
      {"kvishtish": "כביש 90"},
      {"tibis": "טיביס"},
      {"abusalah": "אבו סלאח"},
      {"parasado": "פראסדו"},
      {"cocen": "כפה כוכן"}
     ]
   }
 },
 
 {
  "stores":
    {
    "title": "חנויות",
    "text_path": "content/activities/stores_he.txt",
    "links": 
     [
      {"shufersal": "שופרסל"},
      {"amiad": "חנות קיבוץ עמיעד"},
      {"twentyfourseven": "חנות 24/7"}
     ]
    }
  },
  
  {
  "travel":
    {
    "title": "טיולים",
    "text_path": "content/activities/travel_he.txt",
    "links": 
     [
      {"hokok_beach": "חוף חוקוק"},
      {"nahal_amud": "נחל עמוד"},
      {"butayha": "בטיחה"},
      {"quazrin_pools": "בריכות קצרין"},
      {"hahula": "עמק החולה"},
      {"ein_tina": "עין תינה"},
      {"waterfall": "מפל עיט"},
      {"kayakim": "קייקים"}
     ]
    }
  },
  
  {
  "around_chorazim":
    {
    "title": "סביב כורזים",
    "text_path": "content/activities/around_chorazim_he.txt",
    "links": 
     [
      {"ein_dvir": "עין דביר"}
     ]
    }
  }
  
]
